psusannx_betfair/__init__.py
psusannx_betfair/psusannx_betfair.py
psusannx_betfair-0.0.3.dist-info/LICENSE
psusannx_betfair-0.0.3.dist-info/METADATA
psusannx_betfair-0.0.3.dist-info/WHEEL
psusannx_betfair-0.0.3.dist-info/top_level.txt
psusannx_betfair-0.0.3.dist-info/RECORD
