Metadata-Version: 2.1
Name: psusannx-betfair
Version: 0.0.3
Summary: A package with functions for getting Betfair Exchange odds on upcoming Premier League matches.
Author: Jamie O'Brien
Project-URL: Source Code, https://github.com/jamieob63/psusannx_betfair.git
Project-URL: Bug Tracker, https://github.com/jamieob63/psusannx_betfair.git/issues
License-File: LICENSE
Requires-Dist: numpy
Requires-Dist: pandas
Requires-Dist: requests
